lib/__init__.py
lib/endpoints.py
lib/endpoints_list/__init__.py
lib/endpoints_list/candles.py
lib/endpoints_list/conc_liquidity_positions.py
lib/endpoints_list/contract_logs.py
lib/endpoints_list/dex_trades.py
lib/endpoints_list/lending_market.py
lib/endpoints_list/lending_positions.py
lib/endpoints_list/liquidity_pools.py
lib/endpoints_list/nft_collection.py
lib/endpoints_list/nft_trades.py
lib/endpoints_list/token_acc.py
lib/endpoints_list/token_holders.py
lib/endpoints_list/transfers.py
lib/endpoints_list/trending_contracts.py
parsec_fi-0.0.5.dist-info/METADATA
parsec_fi-0.0.5.dist-info/WHEEL
parsec_fi-0.0.5.dist-info/top_level.txt
parsec_fi-0.0.5.dist-info/RECORD
