Metadata-Version: 2.1
Name: parsec-fi
Version: 0.0.5
Summary: Python SDK for the Parsec API
Home-page: UNKNOWN
Author: PARSEC FINANCE INC.
License: MIT
Platform: UNKNOWN
Requires-Dist: requests
Requires-Dist: pandas
